python_extrac-0.7.0.dist-info/METADATA
python_extrac-0.7.0.dist-info/WHEEL
python_extrac-0.7.0.dist-info/entry_points.txt
python_extrac-0.7.0.dist-info/licenses/LICENSE
python_extrac/__init__.py
python_extrac/ar/__init__.py
python_extrac/ar/__main__.py
python_extrac/bz2/__init__.py
python_extrac/bz2/__main__.py
python_extrac/cab/__init__.py
python_extrac/cab/__main__.py
python_extrac/deb/__init__.py
python_extrac/deb/__main__.py
python_extrac/extrac.py
python_extrac/gz/__init__.py
python_extrac/gz/__main__.py
python_extrac/py7z/__init__.py
python_extrac/py7z/__main__.py
python_extrac/sample/sample.txt
python_extrac/unlzw/__init__.py
python_extrac/unlzw/__main__.py
python_extrac/unlzw/unpack.py
python_extrac/utils.py
python_extrac/xz/__init__.py
python_extrac/xz/__main__.py
python_extrac/zstd/__init__.py
python_extrac/zstd/__main__.py
python_extrac-0.7.0.dist-info/RECORD
